snakemake_executor_plugin_deeporigin/__init__.py
snakemake_executor_plugin_deeporigin-0.3.0.dist-info/LICENSE
snakemake_executor_plugin_deeporigin-0.3.0.dist-info/METADATA
snakemake_executor_plugin_deeporigin-0.3.0.dist-info/WHEEL
snakemake_executor_plugin_deeporigin-0.3.0.dist-info/RECORD
